cli.py
main.py
avatar_everywhere_cli-1.0.4.dist-info/licenses/LICENSE
converters/__init__.py
converters/sandbox_to_vrm.py
node_modules/@adraffy/ens-normalize/README.md
node_modules/@adraffy/ens-normalize/package.json
node_modules/@babel/helper-string-parser/README.md
node_modules/@babel/helper-string-parser/package.json
node_modules/@babel/helper-validator-identifier/README.md
node_modules/@babel/helper-validator-identifier/package.json
node_modules/@babel/parser/CHANGELOG.md
node_modules/@babel/parser/README.md
node_modules/@babel/parser/package.json
node_modules/@babel/types/README.md
node_modules/@babel/types/package.json
node_modules/@coinbase/wallet-sdk/README.md
node_modules/@coinbase/wallet-sdk/package.json
node_modules/@coinbase/wallet-sdk/node_modules/eventemitter3/README.md
node_modules/@coinbase/wallet-sdk/node_modules/eventemitter3/package.json
node_modules/@ethereumjs/common/README.md
node_modules/@ethereumjs/common/package.json
node_modules/@ethereumjs/common/dist/chains/goerli.json
node_modules/@ethereumjs/common/dist/chains/mainnet.json
node_modules/@ethereumjs/common/dist/chains/rinkeby.json
node_modules/@ethereumjs/common/dist/chains/ropsten.json
node_modules/@ethereumjs/common/dist/chains/sepolia.json
node_modules/@ethereumjs/common/dist/eips/1153.json
node_modules/@ethereumjs/common/dist/eips/1559.json
node_modules/@ethereumjs/common/dist/eips/2315.json
node_modules/@ethereumjs/common/dist/eips/2537.json
node_modules/@ethereumjs/common/dist/eips/2565.json
node_modules/@ethereumjs/common/dist/eips/2718.json
node_modules/@ethereumjs/common/dist/eips/2929.json
node_modules/@ethereumjs/common/dist/eips/2930.json
node_modules/@ethereumjs/common/dist/eips/3074.json
node_modules/@ethereumjs/common/dist/eips/3198.json
node_modules/@ethereumjs/common/dist/eips/3529.json
node_modules/@ethereumjs/common/dist/eips/3540.json
node_modules/@ethereumjs/common/dist/eips/3541.json
node_modules/@ethereumjs/common/dist/eips/3554.json
node_modules/@ethereumjs/common/dist/eips/3607.json
avatar_everywhere_cli-1.0.4.dist-info/METADATA
avatar_everywhere_cli-1.0.4.dist-info/WHEEL
avatar_everywhere_cli-1.0.4.dist-info/entry_points.txt
avatar_everywhere_cli-1.0.4.dist-info/top_level.txt
avatar_everywhere_cli-1.0.4.dist-info/RECORD
