Metadata-Version: 2.4
Name: avatar-everywhere-cli
Version: 1.0.4
Summary: Portable Sandbox Identity Toolkit - NFT verification and VRM avatar conversion
Home-page: https://github.com/Supercoolkayy/avatar-everywhere-cli
Author: Abdulkareem Oyeneye/Dapps over Apps.
Author-email: "Abdulkareem Oyeneye/Dapps over Apps." <team@dappsoverapps.com>
Maintainer-email: "Abdulkareem Oyeneye/Dapps over Apps." <team@dappsoverapps.com>
License: MIT
Project-URL: Homepage, https://github.com/Supercoolkayy/avatar-everywhere-cli
Project-URL: Repository, https://github.com/Supercoolkayy/avatar-everywhere-cli
Project-URL: Documentation, https://github.com/Supercoolkayy/avatar-everywhere-cli#readme
Project-URL: Bug Tracker, https://github.com/Supercoolkayy/avatar-everywhere-cli/issues
Keywords: sandbox,avatar,nft,vrm,metaverse,polygon,walletconnect
Classifier: Development Status :: 4 - Beta
Classifier: Intended Audience :: Developers
Classifier: License :: OSI Approved :: MIT License
Classifier: Operating System :: OS Independent
Classifier: Programming Language :: Python :: 3
Classifier: Programming Language :: Python :: 3.10
Classifier: Programming Language :: Python :: 3.11
Classifier: Programming Language :: Python :: 3.12
Classifier: Programming Language :: Python :: 3.13
Classifier: Topic :: Software Development :: Libraries :: Python Modules
Classifier: Topic :: Multimedia :: Graphics :: 3D Modeling
Classifier: Topic :: Internet :: WWW/HTTP :: Dynamic Content
Requires-Python: >=3.10
License-File: LICENSE
Requires-Dist: typer>=0.12.0
Requires-Dist: rich==13.6.0
Requires-Dist: click==8.0.4
Requires-Dist: pygltflib==1.16.1
Requires-Dist: trimesh==4.0.5
Requires-Dist: numpy>=1.26.0
Requires-Dist: pillow>=10.0.0
Requires-Dist: typing-extensions>=4.8.0
Provides-Extra: dev
Requires-Dist: pytest>=7.4.3; extra == "dev"
Requires-Dist: black>=23.9.1; extra == "dev"
Requires-Dist: isort>=5.12.0; extra == "dev"
Requires-Dist: mypy>=1.6.1; extra == "dev"
Requires-Dist: memory-profiler>=0.61.0; extra == "dev"
Requires-Dist: psutil>=5.9.0; extra == "dev"
Provides-Extra: performance
Requires-Dist: memory-profiler>=0.61.0; extra == "performance"
Requires-Dist: psutil>=5.9.0; extra == "performance"
Dynamic: author
Dynamic: home-page
Dynamic: license-file
Dynamic: requires-python
